my_project/__init__.py
my_project/utils/__init__.py
my_project_mala1180-0.2.0.dist-info/LICENSE
my_project_mala1180-0.2.0.dist-info/METADATA
my_project_mala1180-0.2.0.dist-info/WHEEL
my_project_mala1180-0.2.0.dist-info/RECORD
